wellmet/IS_stat.py
wellmet/__init__.py
wellmet/__main__.py
wellmet/candybox.py
wellmet/candynodes.py
wellmet/convex_hull.py
wellmet/estimation.py
wellmet/f_models.py
wellmet/g_models.py
wellmet/ghull.py
wellmet/misc.py
wellmet/reader.py
wellmet/samplebox.py
wellmet/sball.py
wellmet/schemes.py
wellmet/shell.py
wellmet/simplex.py
wellmet/spring.py
wellmet/stm_df.py
wellmet/voronoi.py
wellmet/welford.py
wellmet/whitebox.py
wellmet/wireframe.py
wellmet/dicebox/__init__.py
wellmet/dicebox/_exploration.py
wellmet/dicebox/circumtri.py
wellmet/mplot/__init__.py
wellmet/mplot/_axes3d.py
wellmet/mplot/_axis3d_margins_patch.py
wellmet/mplot/mart.py
wellmet/mplot/mart3d.py
wellmet/mplot/maxes.py
wellmet/mplot/maxes3d.py
wellmet/mplot/mfigs.py
wellmet/mplot/mgraph.py
wellmet/mplot/misc.py
wellmet/qt_gui/__init__.py
wellmet/qt_gui/gl_plot.py
wellmet/qt_gui/gui_startup.py
wellmet/qt_gui/qt_box_functions.py
wellmet/qt_gui/qt_dicebox.py
wellmet/qt_gui/qt_graph_widgets.py
wellmet/qt_gui/qt_gui.py
wellmet/qt_gui/qt_plot.py
wellmet/qt_gui/qt_testcases.py
wellmet/qt_gui/qt_voronoi.py
wellmet/testcases/__init__.py
wellmet/testcases/gaussian_2D.py
wellmet/testcases/testcases_2D.py
wellmet/testcases/testcases_2D_papers.py
wellmet/testcases/testcases_nD.py
wellmet/testcases/testcases_nD_papers.py
wellmet-0.9.7.1.dist-info/LICENSE
wellmet-0.9.7.1.dist-info/METADATA
wellmet-0.9.7.1.dist-info/WHEEL
wellmet-0.9.7.1.dist-info/top_level.txt
wellmet-0.9.7.1.dist-info/RECORD
